hora/README.md
hora/__init__.py
hora/const.py
hora/utils.py
hora/build/lib/horoscope/__init__.py
hora/build/lib/horoscope/main.py
hora/build/lib/horoscope/chart/__init__.py
hora/build/lib/horoscope/chart/arudhas.py
hora/build/lib/horoscope/chart/ashtakavarga.py
hora/build/lib/horoscope/chart/charts.py
hora/build/lib/horoscope/chart/dosha.py
hora/build/lib/horoscope/chart/house.py
hora/build/lib/horoscope/chart/raja_yoga.py
hora/build/lib/horoscope/chart/sphuta.py
hora/build/lib/horoscope/chart/strength.py
hora/build/lib/horoscope/chart/yoga.py
hora/build/lib/horoscope/dhasa/__init__.py
hora/build/lib/horoscope/dhasa/sudharsana_chakra.py
hora/build/lib/horoscope/match/__init__.py
hora/build/lib/horoscope/match/compatibility.py
hora/build/lib/horoscope/prediction/__init__.py
hora/build/lib/horoscope/prediction/general.py
hora/build/lib/horoscope/prediction/longevity.py
hora/build/lib/horoscope/prediction/naadi_marriage.py
hora/build/lib/horoscope/transit/__init__.py
hora/build/lib/horoscope/transit/saham.py
hora/build/lib/horoscope/transit/tajaka.py
hora/build/lib/horoscope/transit/tajaka_yoga.py
hora/build/lib/panchanga/__init__.py
hora/build/lib/panchanga/drik.py
hora/build/lib/panchanga/drik1.py
hora/build/lib/panchanga/khanda_khaadyaka.py
hora/build/lib/panchanga/surya_sidhantha.py
hora/build/lib/panchanga/vratha.py
hora/build/lib/tests/__init__.py
hora/build/lib/tests/book_chart_data.py
hora/build/lib/tests/pvr_tests.py
hora/build/lib/tests/test_ss.py
hora/build/lib/tests/test_ui.py
hora/build/lib/tests/test_yogas.py
hora/build/lib/ui/__init__.py
hora/build/lib/ui/chart_styles.py
hora/build/lib/ui/conjunction_dialog.py
hora/build/lib/ui/horo_chart.py
hora/build/lib/ui/horo_chart_tabs.py
hora/build/lib/ui/match_ui.py
hora/build/lib/ui/vakra_gathi_plot.py
hora/build/lib/ui/vratha_finder.py
hora/data/Marriage_Compatibility-V4.0.1.xlsx
hora/data/all_nak_pad_boy_girl.csv
hora/data/all_nak_pad_boy_girl_south.csv
hora/data/program_inputs.txt
hora/data/uscities.csv
pyhora2-3.5.8.dist-info/LICENSE
pyhora2-3.5.8.dist-info/METADATA
pyhora2-3.5.8.dist-info/WHEEL
pyhora2-3.5.8.dist-info/top_level.txt
pyhora2-3.5.8.dist-info/RECORD
